{"collection": "collocationItems", "type": "array", "data": [{"level": "B2", "text": "___ progress", "q": "自然な語は？", "choices": ["make", "do", "take", "have"], "explain": "make progress。"}, {"level": "B2", "text": "___ the effort", "q": "自然な語は？", "choices": ["make", "do", "take", "have"], "explain": "make the effort。"}, {"level": "B2", "text": "___ homework", "q": "自然な語は？", "choices": ["do", "make", "take", "have"], "explain": "do homework。"}, {"level": "B2", "text": "___ the dishes", "q": "自然な語は？", "choices": ["do", "make", "take", "have"], "explain": "do the dishes。"}, {"level": "B2", "text": "___ business with", "q": "自然な語は？", "choices": ["do", "make", "have", "take"], "explain": "do business with。"}, {"level": "B2", "text": "___ someone a favor", "q": "自然な語は？", "choices": ["do", "make", "take", "give"], "explain": "do someone a favor。"}, {"level": "B2", "text": "___ well", "q": "自然な語は？", "choices": ["do", "make", "take", "have"], "explain": "do well。"}, {"level": "B2", "text": "___ good", "q": "自然な語は？", "choices": ["do", "make", "take", "have"], "explain": "do good（善行）。"}, {"level": "B2", "text": "___ the trick", "q": "自然な語は？", "choices": ["do", "make", "take", "have"], "explain": "do the trick（うまくいく）。"}, {"level": "B2", "text": "___ justice to", "q": "自然な語は？", "choices": ["do", "make", "give", "take"], "explain": "do justice to（正当に扱う）。"}, {"level": "C1", "text": "___ havoc", "q": "自然な語は？", "choices": ["wreak", "make", "do", "take"], "explain": "wreak havoc。"}, {"level": "C1", "text": "___ tribute", "q": "自然な語は？", "choices": ["pay", "give", "make", "do"], "explain": "pay tribute。"}, {"level": "C1", "text": "___ homage to", "q": "自然な語は？", "choices": ["pay", "give", "make", "do"], "explain": "pay homage to。"}, {"level": "C1", "text": "___ heed to", "q": "自然な語は？", "choices": ["pay", "give", "take", "make"], "explain": "pay heed to。"}, {"level": "C1", "text": "___ deference to", "q": "自然な語は？", "choices": ["show", "pay", "give", "make"], "explain": "show deference to。"}, {"level": "C1", "text": "___ commiseration", "q": "自然な語は？", "choices": ["offer", "give", "make", "do"], "explain": "offer commiseration。"}, {"level": "C1", "text": "___ a monopoly on", "q": "自然な語は？", "choices": ["have", "make", "do", "give"], "explain": "have a monopoly on。"}, {"level": "C1", "text": "___ a stronghold", "q": "自然な語は？", "choices": ["have", "take", "hold", "make"], "explain": "have/hold a stronghold。"}, {"level": "C1", "text": "___ a foothold", "q": "自然な語は？", "choices": ["gain", "make", "take", "give"], "explain": "gain a foothold（足がかりを得る）。"}, {"level": "C1", "text": "___ ground", "q": "自然な語は？", "choices": ["gain", "make", "have", "take"], "explain": "gain ground（勢力を増す）。"}, {"level": "C1", "text": "___ momentum", "q": "自然な語は？", "choices": ["gain", "have", "make", "give"], "explain": "gain momentum（勢いを増す）。"}, {"level": "C1", "text": "___ notoriety", "q": "自然な語は？", "choices": ["gain", "make", "have", "give"], "explain": "gain notoriety（悪名を馳せる）。"}, {"level": "C1", "text": "___ acclaim", "q": "自然な語は？", "choices": ["receive", "give", "take", "have"], "explain": "receive acclaim（賞賛される）。"}, {"level": "C1", "text": "___ backlash", "q": "自然な語は？", "choices": ["face", "give", "make", "take"], "explain": "face backlash（反発を受ける）。"}, {"level": "C1", "text": "___ scrutiny", "q": "自然な語は？", "choices": ["face", "give", "make", "take"], "explain": "face scrutiny（精査される）。"}]}